{"timestamp": "Thu Jun 23 16:34:23 2022", "loosers": [{"ticker": "BTEGF", "name": "Baytex Energy Corp.", "change": "-12.82%"}, {"ticker": "CRZBY", "name": "Commerzbank AG", "change": "-12.41%"}, {"ticker": "DB", "name": "Deutsche Bank Aktiengesellschaft", "change": "-11.94%"}, {"ticker": "PLL", "name": "Piedmont Lithium Inc.", "change": "-10.93%"}, {"ticker": "MEGEF", "name": "MEG Energy Corp.", "change": "-10.57%"}, {"ticker": "PBF", "name": "PBF Energy Inc.", "change": "-10.09%"}, {"ticker": "CPG", "name": "Crescent Point Energy Corp.", "change": "-9.68%"}, {"ticker": "BCC", "name": "Boise Cascade Company", "change": "-9.72%"}, {"ticker": "CVI", "name": "CVR Energy, Inc.", "change": "-9.54%"}, {"ticker": "TECK", "name": "Teck Resources Limited", "change": "-9.35%"}, {"ticker": "CNHI", "name": "CNH Industrial N.V.", "change": "-9.12%"}, {"ticker": "AETUF", "name": "ARC Resources Ltd.", "change": "-8.85%"}, {"ticker": "CF", "name": "CF Industries Holdings, Inc.", "change": "-8.83%"}, {"ticker": "AR", "name": "Antero Resources Corporation", "change": "-8.65%"}, {"ticker": "NNGRY", "name": "NN Group N.V.", "change": "-8.65%"}, {"ticker": "ERF", "name": "Enerplus Corporation", "change": "-8.52%"}, {"ticker": "VET", "name": "Vermilion Energy Inc.", "change": "-8.39%"}, {"ticker": "ARCH", "name": "Arch Resources, Inc.", "change": "-8.46%"}, {"ticker": "MOS", "name": "The Mosaic Company", "change": "-8.33%"}, {"ticker": "SPGYF", "name": "Whitecap Resources Inc.", "change": "-8.32%"}, {"ticker": "AGCO", "name": "AGCO Corporation", "change": "-8.30%"}, {"ticker": "CRK", "name": "Comstock Resources, Inc.", "change": "-8.07%"}, {"ticker": "RRC", "name": "Range Resources Corporation", "change": "-8.13%"}, {"ticker": "FEAM", "name": "5E Advanced Materials Inc.", "change": "-8.10%"}, {"ticker": "SLB", "name": "Schlumberger Limited", "change": "-7.86%"}]}