{"timestamp": "Tue Jan 11 19:18:37 2022", "loosers": [{"ticker": "AAGH", "name": "America Great Health", "change": null}, {"ticker": "PACB", "name": "Pacific Biosciences of California, Inc.", "change": null}, {"ticker": "ACI", "name": "Albertsons Companies, Inc.", "change": null}, {"ticker": "SWTX", "name": "SpringWorks Therapeutics, Inc.", "change": null}, {"ticker": "TRSWF", "name": "TransAlta Renewables Inc.", "change": null}, {"ticker": "KSRYY", "name": "KOS\u00c9 Corporation", "change": null}, {"ticker": "APLS", "name": "Apellis Pharmaceuticals, Inc.", "change": null}, {"ticker": "SFM", "name": "Sprouts Farmers Market, Inc.", "change": null}, {"ticker": "QFIN", "name": "360 DigiTech, Inc.", "change": null}, {"ticker": "PTAIF", "name": "PT Astra International Tbk", "change": null}, {"ticker": "FBASF", "name": "Fibra UNO", "change": null}, {"ticker": "TAC", "name": "TransAlta Corporation", "change": null}, {"ticker": "CRHKY", "name": "China Resources Beer (Holdings) Company Limited", "change": null}, {"ticker": "SSDOY", "name": "Shiseido Company, Limited", "change": null}, {"ticker": "INSM", "name": "Insmed Incorporated", "change": null}, {"ticker": "BNTX", "name": "BioNTech SE", "change": null}, {"ticker": "MRNA", "name": "Moderna, Inc.", "change": null}, {"ticker": "NVNXF", "name": "Novonix Limited", "change": null}, {"ticker": "SFBQF", "name": "SoftBank Corp.", "change": null}, {"ticker": "PHJMF", "name": "PT Hanjaya Mandala Sampoerna Tbk", "change": null}, {"ticker": "TXG", "name": "10x Genomics, Inc.", "change": null}, {"ticker": "KOD", "name": "Kodiak Sciences Inc.", "change": null}, {"ticker": "BJ", "name": "BJ's Wholesale Club Holdings, Inc.", "change": null}, {"ticker": "FIGS", "name": "FIGS, Inc.", "change": null}, {"ticker": "CDNA", "name": "CareDx, Inc", "change": null}]}