{"timestamp": "Mon Aug 16 15:25:24 2021", "loosers": [{"ticker": "OSCR", "name": "Oscar Health, Inc.", "change": "-14.12%"}, {"ticker": "PSFE", "name": "Paysafe Limited", "change": "-13.58%"}, {"ticker": "TSSLF", "name": "Telesites, S.A.B. de C.V.", "change": "-13.33%"}, {"ticker": "ZIP", "name": "ZipRecruiter, Inc.", "change": "-10.52%"}, {"ticker": "BNTX", "name": "BioNTech SE", "change": "-9.86%"}, {"ticker": "UWMC", "name": "UWM Holdings Corporation", "change": "-9.72%"}, {"ticker": "RLX", "name": "RLX Technology Inc.", "change": "-9.26%"}, {"ticker": "NVAX", "name": "Novavax, Inc.", "change": "-8.93%"}, {"ticker": "EXPI", "name": "eXp World Holdings, Inc.", "change": "-8.81%"}, {"ticker": "WISH", "name": "ContextLogic Inc.", "change": "-8.54%"}, {"ticker": "FUTU", "name": "Futu Holdings Limited", "change": "-8.47%"}, {"ticker": "FFIE", "name": "Faraday Future Intelligent Electric Inc.", "change": "-8.31%"}, {"ticker": "RERE", "name": "AiHuiShou International Co. Ltd.", "change": "-8.53%"}, {"ticker": "SHLS", "name": "Shoals Technologies Group, Inc.", "change": "-8.41%"}, {"ticker": "NPSNY", "name": "Naspers Limited", "change": "-8.29%"}, {"ticker": "YOU", "name": "Clear Secure, Inc.", "change": "-8.21%"}, {"ticker": "BYDDY", "name": "BYD Company Limited", "change": "-7.92%"}, {"ticker": "DOMA", "name": "Doma Holdings Inc.", "change": "-7.92%"}, {"ticker": "DSEY", "name": "Diversey Holdings, Ltd.", "change": "-7.86%"}, {"ticker": "GNENF", "name": "Ganfeng Lithium Co., Ltd.", "change": "-7.75%"}, {"ticker": "BYDDF", "name": "BYD Company Limited", "change": "-7.69%"}, {"ticker": "GDRX", "name": "GoodRx Holdings, Inc.", "change": "-7.74%"}, {"ticker": "GELYF", "name": "Geely Automobile Holdings Limited", "change": "-7.67%"}, {"ticker": "BODY", "name": "The Beachbody Company, Inc.", "change": "-7.79%"}, {"ticker": "DADA", "name": "Dada Nexus Limited", "change": "-7.59%"}]}