{"timestamp": "Tue Feb 15 19:16:14 2022", "loosers": [{"ticker": "MEDP", "name": "Medpace Holdings, Inc.", "change": "-20.35%"}, {"ticker": "CAR", "name": "Avis Budget Group, Inc.", "change": "-11.30%"}, {"ticker": "RCRUY", "name": "Recruit Holdings Co., Ltd.", "change": "-8.90%"}, {"ticker": "FIS", "name": "Fidelity National Information Services, Inc.", "change": "-8.79%"}, {"ticker": "HMY", "name": "Harmony Gold Mining Company Limited", "change": "-8.35%"}, {"ticker": "PRI", "name": "Primerica, Inc.", "change": "-8.07%"}, {"ticker": "CYTK", "name": "Cytokinetics, Incorporated", "change": "-7.70%"}, {"ticker": "IPGP", "name": "IPG Photonics Corporation", "change": "-7.25%"}, {"ticker": "SYNH", "name": "Syneos Health, Inc.", "change": "-6.89%"}, {"ticker": "KUBTY", "name": "Kubota Corporation", "change": "-6.42%"}, {"ticker": "CLR", "name": "Continental Resources, Inc.", "change": "-5.74%"}, {"ticker": "IQV", "name": "IQVIA Holdings Inc.", "change": "-5.95%"}, {"ticker": "PTR", "name": "PetroChina Company Limited", "change": "-5.79%"}, {"ticker": "OMCL", "name": "Omnicell, Inc.", "change": "-5.75%"}, {"ticker": "STZ", "name": "Constellation Brands, Inc.", "change": "-5.56%"}, {"ticker": "ICLR", "name": "ICON Public Limited Company", "change": "-5.58%"}, {"ticker": "CGSHY", "name": "Country Garden Services Holdings Company Limited", "change": "-5.45%"}, {"ticker": "RYDAF", "name": "Shell plc", "change": "-5.25%"}, {"ticker": "SBSW", "name": "Sibanye Stillwater Limited", "change": "-5.04%"}, {"ticker": "IONQ", "name": "IonQ, Inc.", "change": "-5.14%"}, {"ticker": "OLK", "name": "Olink Holding AB (publ)", "change": "-5.00%"}, {"ticker": "PHJMF", "name": "PT Hanjaya Mandala Sampoerna Tbk", "change": "-4.83%"}, {"ticker": "EQNR", "name": "Equinor ASA", "change": "-4.70%"}, {"ticker": "ARVN", "name": "Arvinas, Inc.", "change": "-4.76%"}, {"ticker": "EGRNF", "name": "China Evergrande Group", "change": "-4.79%"}]}