{"timestamp": "Wed May 11 16:36:57 2022", "loosers": [{"ticker": "U", "name": "Unity Software Inc.", "change": "-34.14%"}, {"ticker": "HUATF", "name": "Huatai Securities Co., Ltd.", "change": "-31.59%"}, {"ticker": "COIN", "name": "Coinbase Global, Inc.", "change": "-23.34%"}, {"ticker": "NVAX", "name": "Novavax, Inc.", "change": "-16.13%"}, {"ticker": "MSTR", "name": "MicroStrategy Incorporated", "change": "-16.12%"}, {"ticker": "MDDNF", "name": "Meridian Energy Limited", "change": "-15.94%"}, {"ticker": "AFRM", "name": "Affirm Holdings, Inc.", "change": "-14.84%"}, {"ticker": "UPST", "name": "Upstart Holdings, Inc.", "change": "-14.49%"}, {"ticker": "CHVKF", "name": "China Vanke Co., Ltd.", "change": "-14.30%"}, {"ticker": "KGDEF", "name": "Kingdee International Software Group Company Limited", "change": "-14.22%"}, {"ticker": "BGNE", "name": "BeiGene, Ltd.", "change": "-14.14%"}, {"ticker": "JXN", "name": "Jackson Financial Inc.", "change": "-14.34%"}, {"ticker": "NICMF", "name": "Nickel Mines Limited", "change": "-13.68%"}, {"ticker": "DISH", "name": "DISH Network Corporation", "change": "-13.98%"}, {"ticker": "BSY", "name": "Bentley Systems, Incorporated", "change": "-12.06%"}, {"ticker": "EVO", "name": "Evotec SE", "change": "-11.98%"}, {"ticker": "SQ", "name": "Block, Inc.", "change": "-10.81%"}, {"ticker": "AUR", "name": "Aurora Innovation, Inc.", "change": "-10.98%"}, {"ticker": "BRPHF", "name": "Galaxy Digital Holdings Ltd.", "change": "-10.32%"}, {"ticker": "SG", "name": "Sweetgreen, Inc.", "change": "-10.53%"}, {"ticker": "CPNG", "name": "Coupang, Inc.", "change": "-10.30%"}, {"ticker": "WEN", "name": "The Wendy's Company", "change": "-10.06%"}, {"ticker": "IPAR", "name": "Inter Parfums, Inc.", "change": "-10.01%"}, {"ticker": "AMC", "name": "AMC Entertainment Holdings, Inc.", "change": "-9.63%"}, {"ticker": "MNDY", "name": "monday.com Ltd.", "change": "-9.70%"}]}