{"timestamp": "Wed Jun 29 20:26:26 2022", "loosers": [{"ticker": "JTKWY", "name": "Just Eat Takeaway.com N.V.", "change": "-16.17%"}, {"ticker": "AANNF", "name": "Aroundtown SA", "change": "-14.42%"}, {"ticker": "CCL", "name": "Carnival Corporation & plc", "change": "-14.13%"}, {"ticker": "CUK", "name": "Carnival Corporation & plc", "change": "-13.71%"}, {"ticker": "SPWR", "name": "SunPower Corporation", "change": "-10.78%"}, {"ticker": "MNSO", "name": "MINISO Group Holding Limited", "change": "-10.67%"}, {"ticker": "BBVXF", "name": "Banco Bilbao Vizcaya Argentaria, S.A.", "change": "-10.56%"}, {"ticker": "YMM", "name": "Full Truck Alliance Co. Ltd.", "change": "-10.53%"}, {"ticker": "RCL", "name": "Royal Caribbean Cruises Ltd.", "change": "-10.26%"}, {"ticker": "UPST", "name": "Upstart Holdings, Inc.", "change": "-10.21%"}, {"ticker": "GWLLF", "name": "Great Wall Motor Company Limited", "change": "-9.33%"}, {"ticker": "NCLH", "name": "Norwegian Cruise Line Holdings Ltd.", "change": "-9.33%"}, {"ticker": "NUTX", "name": "Nutex Health, Inc.", "change": "-9.26%"}, {"ticker": "ENTG", "name": "Entegris, Inc.", "change": "-9.24%"}, {"ticker": "JOBY", "name": "Joby Aviation, Inc.", "change": "-9.11%"}, {"ticker": "BBWI", "name": "Bath & Body Works, Inc.", "change": "-8.97%"}, {"ticker": "SWN", "name": "Southwestern Energy Company", "change": "-8.96%"}, {"ticker": "BTLCY", "name": "British Land Company Plc", "change": "-8.85%"}, {"ticker": "AFLYY", "name": "Air France-KLM SA", "change": "-8.77%"}, {"ticker": "STNG", "name": "Scorpio Tankers Inc.", "change": "-8.54%"}, {"ticker": "CPE", "name": "Callon Petroleum Company", "change": "-8.51%"}, {"ticker": "NOG", "name": "Northern Oil and Gas, Inc.", "change": "-8.41%"}, {"ticker": "MNKPF", "name": "Mallinckrodt plc", "change": "-8.41%"}, {"ticker": "CVT", "name": "Cvent Holding Corp.", "change": "-8.37%"}, {"ticker": "LAZR", "name": "Luminar Technologies, Inc.", "change": "-8.01%"}]}