{"timestamp": "Thu Jan  6 18:27:30 2022", "loosers": [{"ticker": "EMBK", "name": "Embark Technology, Inc.", "change": null}, {"ticker": "HUM", "name": "Humana Inc.", "change": null}, {"ticker": "NXE", "name": "NexGen Energy Ltd.", "change": null}, {"ticker": "JOBY", "name": "Joby Aviation, Inc.", "change": null}, {"ticker": "STZHF", "name": "Stelco Holdings Inc.", "change": null}, {"ticker": "WPLCF", "name": "Wise plc", "change": null}, {"ticker": "ADT", "name": "ADT Inc.", "change": null}, {"ticker": "AZZVF", "name": "AVZ Minerals Limited", "change": null}, {"ticker": "ITMPF", "name": "ITM Power Plc", "change": null}, {"ticker": "RIVN", "name": "Rivian Automotive, Inc.", "change": null}, {"ticker": "DDL", "name": "Dingdong (Cayman) Limited", "change": null}, {"ticker": "APTPF", "name": "Airports of Thailand Public Company Limited", "change": null}, {"ticker": "MNDY", "name": "monday.com Ltd.", "change": null}, {"ticker": "HMY", "name": "Harmony Gold Mining Company Limited", "change": null}, {"ticker": "NLLSF", "name": "Nel ASA", "change": null}, {"ticker": "NVNXF", "name": "Novonix Limited", "change": null}, {"ticker": "CIG-C", "name": "Companhia Energ\u00e9tica de Minas Gerais", "change": null}, {"ticker": "CCJ", "name": "Cameco Corporation", "change": null}, {"ticker": "PILBF", "name": "Pilbara Minerals Limited", "change": null}, {"ticker": "AMPL", "name": "Amplitude, Inc.", "change": null}, {"ticker": "WIZEY", "name": "Wise plc", "change": null}, {"ticker": "LOGI", "name": "Logitech International S.A.", "change": null}, {"ticker": "OSH", "name": "Oak Street Health, Inc.", "change": null}, {"ticker": "CNM", "name": "Core & Main, Inc.", "change": null}, {"ticker": "DIDI", "name": "DiDi Global Inc.", "change": null}]}