{"timestamp": "Mon Mar 22 19:19:01 2021", "loosers": [{"ticker": "NOKPF", "name": "Nok Airlines Public Company Limited", "change": "-59.04%"}, {"ticker": "TAWNF", "name": "Thai Airways International Public Company Limited", "change": "-54.55%"}, {"ticker": "RLX", "name": "RLX Technology Inc.", "change": "-47.38%"}, {"ticker": "NWAU", "name": "Consumer Automotive Finance, Inc.", "change": "-44.44%"}, {"ticker": "TKGBY", "name": "Turkiye Garanti Bankasi A.S.", "change": "-15.87%"}, {"ticker": "CAN", "name": "Canaan Inc.", "change": "-17.81%"}, {"ticker": "AKBTY", "name": "Akbank T.A.S.", "change": "-16.93%"}, {"ticker": "TKC", "name": "Turkcell Iletisim Hizmetleri A.S.", "change": "-11.48%"}, {"ticker": "AMC", "name": "AMC Entertainment Holdings, Inc.", "change": "-11.23%"}, {"ticker": "DNMR", "name": "Danimer Scientific, Inc.", "change": "-11.26%"}, {"ticker": "RAAS", "name": "Cloopen Group Holding Limited", "change": "-10.99%"}, {"ticker": "BCRX", "name": "BioCryst Pharmaceuticals, Inc.", "change": "-10.42%"}, {"ticker": "CNNWF", "name": "Cineworld Group plc", "change": "-10.34%"}, {"ticker": "TRIP", "name": "TripAdvisor, Inc.", "change": "-9.35%"}, {"ticker": "JBLU", "name": "JetBlue Airways Corporation", "change": "-8.79%"}, {"ticker": "HIMS", "name": "Hims & Hers Health, Inc.", "change": "-8.60%"}, {"ticker": "RIOT", "name": "Riot Blockchain, Inc.", "change": "-8.39%"}, {"ticker": "ZIM", "name": "ZIM Integrated Shipping Services Ltd.", "change": "-7.49%"}, {"ticker": "MARA", "name": "Marathon Digital Holdings, Inc.", "change": "-7.92%"}, {"ticker": "MTSI", "name": "MACOM Technology Solutions Holdings, Inc.", "change": "-7.34%"}, {"ticker": "BBVA", "name": "Banco Bilbao Vizcaya Argentaria, S.A.", "change": "-7.17%"}, {"ticker": "EH", "name": "EHang Holdings Limited", "change": "-7.67%"}, {"ticker": "RYCEY", "name": "Rolls-Royce Holdings plc", "change": "-6.51%"}, {"ticker": "QFIN", "name": "360 DigiTech, Inc.", "change": "-6.32%"}, {"ticker": "MSTR", "name": "MicroStrategy Incorporated", "change": "-6.34%"}]}