{"timestamp": "Thu Jun  2 13:51:00 2022", "loosers": [{"ticker": "NUTX", "name": "Nutex Health, Inc.", "change": "-9.10%"}, {"ticker": "CPE", "name": "Callon Petroleum Company", "change": "-7.60%"}, {"ticker": "HPE", "name": "Hewlett Packard Enterprise Company", "change": "-7.45%"}, {"ticker": "EQRX", "name": "EQRx, Inc.", "change": "-7.91%"}, {"ticker": "CIEN", "name": "Ciena Corporation", "change": "-7.44%"}, {"ticker": "BMRPF", "name": "B&M European Value Retail S.A.", "change": "0.00%"}, {"ticker": "CCI", "name": "Crown Castle International Corp.", "change": "-5.72%"}, {"ticker": "HPK", "name": "HighPeak Energy, Inc.", "change": "-4.28%"}, {"ticker": "REGN", "name": "Regeneron Pharmaceuticals, Inc.", "change": "-5.75%"}, {"ticker": "MGY", "name": "Magnolia Oil & Gas Corporation", "change": "-5.61%"}, {"ticker": "DSNKY", "name": "Daiichi Sankyo Company, Limited", "change": "+0.56%"}, {"ticker": "RYLPF", "name": "Koninklijke Philips N.V.", "change": "0.00%"}, {"ticker": "FMS", "name": "Fresenius Medical Care AG & Co. KGaA", "change": "-4.89%"}, {"ticker": "MTHRY", "name": "M3, Inc.", "change": "-2.87%"}, {"ticker": "HRL", "name": "Hormel Foods Corporation", "change": "-4.66%"}, {"ticker": "KHC", "name": "The Kraft Heinz Company", "change": "-4.11%"}, {"ticker": "SBAC", "name": "SBA Communications Corporation", "change": "-4.14%"}, {"ticker": "CIVI", "name": "Civitas Resources, Inc.", "change": "-3.99%"}, {"ticker": "PARA", "name": "Paramount Global", "change": "-3.99%"}, {"ticker": "LU", "name": "Lufax Holding Ltd", "change": "-4.06%"}, {"ticker": "MCK", "name": "McKesson Corporation", "change": "-3.68%"}, {"ticker": "KB", "name": "KB Financial Group Inc.", "change": "-3.48%"}, {"ticker": "AJINY", "name": "Ajinomoto Co., Inc.", "change": "-1.32%"}, {"ticker": "DASH", "name": "DoorDash, Inc.", "change": "-2.70%"}, {"ticker": "BTGOF", "name": "BT Group plc", "change": "-3.20%"}]}