{"timestamp": "Tue May 31 20:27:09 2022", "loosers": [{"ticker": "GFI", "name": "Gold Fields Limited", "change": "-23.44%"}, {"ticker": "BMRRY", "name": "B&M European Value Retail S.A.", "change": "-14.36%"}, {"ticker": "CVNA", "name": "Carvana Co.", "change": "-13.03%"}, {"ticker": "LAC", "name": "Lithium Americas Corp.", "change": "-12.83%"}, {"ticker": "RLLCF", "name": "Rolls-Royce Holdings plc", "change": "-12.50%"}, {"ticker": "S", "name": "SentinelOne, Inc.", "change": "-11.79%"}, {"ticker": "NTRA", "name": "Natera, Inc.", "change": "-10.92%"}, {"ticker": "BMRPF", "name": "B&M European Value Retail S.A.", "change": "-10.54%"}, {"ticker": "AMR", "name": "Alpha Metallurgical Resources, Inc.", "change": "-9.78%"}, {"ticker": "TKGBY", "name": "Turkiye Garanti Bankasi A.S.", "change": "-9.71%"}, {"ticker": "SNAP", "name": "Snap Inc.", "change": "-9.44%"}, {"ticker": "GME", "name": "GameStop Corp.", "change": "-9.09%"}, {"ticker": "GTLB", "name": "GitLab Inc.", "change": "-9.32%"}, {"ticker": "PODD", "name": "Insulet Corporation", "change": "-9.24%"}, {"ticker": "ARCH", "name": "Arch Resources, Inc.", "change": "-9.15%"}, {"ticker": "MRVI", "name": "Maravai LifeSciences Holdings, Inc.", "change": "-9.13%"}, {"ticker": "UDMY", "name": "Udemy, Inc.", "change": "-9.06%"}, {"ticker": "NTCT", "name": "NetScout Systems, Inc.", "change": "-8.82%"}, {"ticker": "CHWY", "name": "Chewy, Inc.", "change": "-8.52%"}, {"ticker": "HMY", "name": "Harmony Gold Mining Company Limited", "change": "-8.17%"}, {"ticker": "QDEL", "name": "QuidelOrtho Corporation", "change": "-8.14%"}, {"ticker": "CWAN", "name": "Clearwater Analytics Holdings, Inc.", "change": "-8.08%"}, {"ticker": "DKNG", "name": "DraftKings Inc.", "change": "-7.95%"}, {"ticker": "BB", "name": "BlackBerry Limited", "change": "-7.91%"}, {"ticker": "NPNYY", "name": "Nippon Yusen Kabushiki Kaisha", "change": "-7.88%"}]}