{"timestamp": "Thu May 18 17:15:34 2023", "loosers": [{"ticker": "AULT", "name": "Ault Alliance, Inc.", "change": "-16.57%"}, {"ticker": "BOWL", "name": "Bowlero Corp.", "change": "-15.50%"}, {"ticker": "GRAB", "name": "Grab Holdings Limited", "change": "-13.66%"}, {"ticker": "IBRX", "name": "ImmunityBio, Inc.", "change": "-13.31%"}, {"ticker": "STNE", "name": "StoneCo Ltd.", "change": "-8.76%"}, {"ticker": "LU", "name": "Lufax Holding Ltd", "change": "-8.24%"}, {"ticker": "FUTU", "name": "Futu Holdings Limited", "change": "-7.62%"}, {"ticker": "VIPS", "name": "Vipshop Holdings Limited", "change": "-7.46%"}, {"ticker": "BTGOF", "name": "BT Group plc", "change": "-7.41%"}, {"ticker": "PDD", "name": "PDD Holdings Inc.", "change": "-7.13%"}, {"ticker": "LUMN", "name": "Lumen Technologies, Inc.", "change": "-6.63%"}, {"ticker": "BEKE", "name": "KE Holdings Inc.", "change": "-6.72%"}, {"ticker": "KD", "name": "Kyndryl Holdings, Inc.", "change": "-6.26%"}, {"ticker": "ATHM", "name": "Autohome Inc.", "change": "-6.51%"}, {"ticker": "QFIN", "name": "Qifu Technology, Inc.", "change": "-6.52%"}, {"ticker": "VKTX", "name": "Viking Therapeutics, Inc.", "change": "-6.17%"}, {"ticker": "ATAT", "name": "Atour Lifestyle Holdings Limited", "change": "-6.05%"}, {"ticker": "MNSO", "name": "MINISO Group Holding Limited", "change": "-6.09%"}, {"ticker": "HCM", "name": "HUTCHMED (China) Limited", "change": "-6.14%"}, {"ticker": "ZLAB", "name": "Zai Lab Limited", "change": "-5.52%"}, {"ticker": "EONGY", "name": "E.ON SE", "change": "-5.54%"}, {"ticker": "AKBTY", "name": "Akbank T.A.S.", "change": "-5.23%"}, {"ticker": "DQ", "name": "Daqo New Energy Corp.", "change": "-4.94%"}, {"ticker": "TGTX", "name": "TG Therapeutics, Inc.", "change": "-4.93%"}, {"ticker": "PROK", "name": "ProKidney Corp.", "change": "-4.91%"}]}