{"timestamp": "Fri Nov 25 20:22:09 2022", "loosers": [{"ticker": "LU", "name": "Lufax Holding Ltd", "change": "-20.00%"}, {"ticker": "CITAF", "name": "COSCO SHIPPING Development Co., Ltd.", "change": "-11.56%"}, {"ticker": "PILBF", "name": "Pilbara Minerals Limited", "change": "-10.32%"}, {"ticker": "LTHM", "name": "Livent Corporation", "change": "-8.81%"}, {"ticker": "YMM", "name": "Full Truck Alliance Co. Ltd.", "change": "-8.20%"}, {"ticker": "BILI", "name": "Bilibili Inc.", "change": "-7.15%"}, {"ticker": "LAC", "name": "Lithium Americas Corp.", "change": "-7.05%"}, {"ticker": "SQM", "name": "Sociedad Qu\u00edmica y Minera de Chile S.A.", "change": "-6.80%"}, {"ticker": "LKNCY", "name": "Luckin Coffee Inc.", "change": "-6.74%"}, {"ticker": "BKRIY", "name": "Bank of Ireland Group plc", "change": "-6.71%"}, {"ticker": "FUTU", "name": "Futu Holdings Limited", "change": "-6.51%"}, {"ticker": "CS", "name": "Credit Suisse Group AG", "change": "-6.27%"}, {"ticker": "SGIOY", "name": "Shionogi & Co., Ltd.", "change": "-6.07%"}, {"ticker": "VCTR", "name": "Victory Capital Holdings, Inc.", "change": "-5.75%"}, {"ticker": "RLX", "name": "RLX Technology Inc.", "change": "-5.53%"}, {"ticker": "ATHM", "name": "Autohome Inc.", "change": "-5.34%"}, {"ticker": "JD", "name": "JD.com, Inc.", "change": "-5.32%"}, {"ticker": "BZ", "name": "Kanzhun Limited", "change": "-5.10%"}, {"ticker": "ZLAB", "name": "Zai Lab Limited", "change": "-4.97%"}, {"ticker": "GELYY", "name": "Geely Automobile Holdings Limited", "change": "-4.88%"}, {"ticker": "TCEHY", "name": "Tencent Holdings Limited", "change": "-4.71%"}, {"ticker": "WB", "name": "Weibo Corporation", "change": "-4.63%"}, {"ticker": "NRILY", "name": "Nomura Research Institute, Ltd.", "change": "-4.54%"}, {"ticker": "SSL", "name": "Sasol Limited", "change": "-4.33%"}, {"ticker": "TCOM", "name": "Trip.com Group Limited", "change": "-4.28%"}]}