{"timestamp": "Fri Dec 17 20:19:20 2021", "loosers": [{"ticker": "TKGBY", "name": "Turkiye Garanti Bankasi A.S.", "change": null}, {"ticker": "RIVN", "name": "Rivian Automotive, Inc.", "change": null}, {"ticker": "NVO", "name": "Novo Nordisk A/S", "change": null}, {"ticker": "JDCMF", "name": "JD.com, Inc.", "change": null}, {"ticker": "NU", "name": "Nu Holdings Ltd.", "change": null}, {"ticker": "ORCL", "name": "Oracle Corporation", "change": null}, {"ticker": "CLLNY", "name": "Cellnex Telecom, S.A.", "change": null}, {"ticker": "DSEY", "name": "Diversey Holdings, Ltd.", "change": null}, {"ticker": "CPG", "name": "Crescent Point Energy Corp.", "change": null}, {"ticker": "DSKYF", "name": "Daiichi Sankyo Company, Limited", "change": null}, {"ticker": "ERF", "name": "Enerplus Corporation", "change": null}, {"ticker": "LOB", "name": "Live Oak Bancshares, Inc.", "change": null}, {"ticker": "HESAY", "name": "Herm\u00e8s International Soci\u00e9t\u00e9 en commandite par actions", "change": null}, {"ticker": "AKBTY", "name": "Akbank T.A.S.", "change": null}, {"ticker": "SG", "name": "Sweetgreen, Inc.", "change": null}, {"ticker": "BLD", "name": "TopBuild Corp.", "change": null}, {"ticker": "BCAUY", "name": "Brilliance China Automotive Holdings Limited", "change": null}, {"ticker": "WEICY", "name": "Weichai Power Co., Ltd.", "change": null}, {"ticker": "EGRNF", "name": "China Evergrande Group", "change": null}, {"ticker": "MARA", "name": "Marathon Digital Holdings, Inc.", "change": null}, {"ticker": "GM", "name": "General Motors Company", "change": null}, {"ticker": "DRI", "name": "Darden Restaurants, Inc.", "change": null}, {"ticker": "NVNXF", "name": "Novonix Limited", "change": null}, {"ticker": "HES", "name": "Hess Corporation", "change": null}, {"ticker": "VWAGY", "name": "Volkswagen AG", "change": null}]}