{"timestamp": "Wed Nov 30 21:19:12 2022", "loosers": [{"ticker": "CRWD", "name": "CrowdStrike Holdings, Inc.", "change": "-15.43%"}, {"ticker": "APE", "name": "AMC Entertainment Holdings, Inc.", "change": "-12.85%"}, {"ticker": "S", "name": "SentinelOne, Inc.", "change": "-7.64%"}, {"ticker": "NTAP", "name": "NetApp, Inc.", "change": "-5.79%"}, {"ticker": "NVST", "name": "Envista Holdings Corporation", "change": "-5.33%"}, {"ticker": "CRL", "name": "Charles River Laboratories International, Inc.", "change": "-5.15%"}, {"ticker": "WARFY", "name": "Wharf (Holdings) Limited", "change": "-4.76%"}, {"ticker": "RBSPF", "name": "NatWest Group plc", "change": "-4.70%"}, {"ticker": "TIIAY", "name": "Telecom Italia S.p.A.", "change": "-4.46%"}, {"ticker": "PBF", "name": "PBF Energy Inc.", "change": "-4.06%"}, {"ticker": "BKRKF", "name": "PT Bank Rakyat Indonesia (Persero) Tbk", "change": "-3.79%"}, {"ticker": "ABCL", "name": "AbCellera Biologics Inc.", "change": "-3.67%"}, {"ticker": "GEF-B", "name": "Greif, Inc.", "change": "-3.66%"}, {"ticker": "HCM", "name": "HUTCHMED (China) Limited", "change": "-3.39%"}, {"ticker": "LESL", "name": "Leslie's, Inc.", "change": "-3.49%"}, {"ticker": "CODQL", "name": "Coronado Global Resources Inc.", "change": "-3.33%"}, {"ticker": "HRL", "name": "Hormel Foods Corporation", "change": "-2.99%"}, {"ticker": "AMC", "name": "AMC Entertainment Holdings, Inc.", "change": "-3.36%"}, {"ticker": "DTCWY", "name": "Deutsche Wohnen SE", "change": "-3.01%"}, {"ticker": "BTLCY", "name": "British Land Company Plc", "change": "-2.88%"}, {"ticker": "GEF", "name": "Greif, Inc.", "change": "-2.62%"}, {"ticker": "CORT", "name": "Corcept Therapeutics Incorporated", "change": "-2.33%"}]}