{"timestamp": "Wed Feb 15 17:19:17 2023", "loosers": [{"ticker": "DVN", "name": "Devon Energy Corporation", "change": "-12.36%"}, {"ticker": "HL", "name": "Hecla Mining Company", "change": "-10.53%"}, {"ticker": "AKAM", "name": "Akamai Technologies, Inc.", "change": "-10.22%"}, {"ticker": "BCS", "name": "Barclays PLC", "change": "-9.27%"}, {"ticker": "LAD", "name": "Lithia Motors, Inc.", "change": "-8.36%"}, {"ticker": "AU", "name": "AngloGold Ashanti Limited", "change": "-6.60%"}, {"ticker": "KB", "name": "KB Financial Group Inc.", "change": "-6.39%"}, {"ticker": "ANGPY", "name": "Anglo American Platinum Limited", "change": "-6.29%"}, {"ticker": "TSM", "name": "Taiwan Semiconductor Manufacturing Company Limited", "change": "-6.24%"}, {"ticker": "MEDP", "name": "Medpace Holdings, Inc.", "change": "-5.95%"}, {"ticker": "KEP", "name": "Korea Electric Power Corporation", "change": "-5.57%"}, {"ticker": "CPE", "name": "Callon Petroleum Company", "change": "-5.65%"}, {"ticker": "DADA", "name": "Dada Nexus Limited", "change": "-5.38%"}, {"ticker": "MRO", "name": "Marathon Oil Corporation", "change": "-5.43%"}, {"ticker": "GXO", "name": "GXO Logistics, Inc.", "change": "-5.00%"}, {"ticker": "TIGO", "name": "Millicom International Cellular S.A.", "change": "-5.29%"}, {"ticker": "GELYF", "name": "Geely Automobile Holdings Limited", "change": "-5.19%"}, {"ticker": "KGC", "name": "Kinross Gold Corporation", "change": "-5.30%"}, {"ticker": "SCI", "name": "Service Corporation International", "change": "-5.20%"}, {"ticker": "SHG", "name": "Shinhan Financial Group Co., Ltd.", "change": "-5.08%"}, {"ticker": "DY", "name": "Dycom Industries, Inc.", "change": "-5.07%"}, {"ticker": "PXD", "name": "Pioneer Natural Resources Company", "change": "-5.18%"}, {"ticker": "OXY", "name": "Occidental Petroleum Corporation", "change": "-4.97%"}, {"ticker": "FTCH", "name": "Farfetch Limited", "change": "-4.84%"}, {"ticker": "STR", "name": "Sitio Royalties Corp.", "change": "-4.83%"}]}