{"timestamp": "Mon Sep 19 20:29:13 2022", "loosers": [{"ticker": "SHC", "name": "Sotera Health Company", "change": "-33.27%"}, {"ticker": "HKD", "name": "AMTD Digital Inc.", "change": "-14.81%"}, {"ticker": "PGY", "name": "Pagaya Technologies Ltd.", "change": "-11.18%"}, {"ticker": "IBRX", "name": "ImmunityBio, Inc.", "change": "-9.08%"}, {"ticker": "BNTX", "name": "BioNTech SE", "change": "-8.60%"}, {"ticker": "CGSHY", "name": "Country Garden Services Holdings Company Limited", "change": "-8.06%"}, {"ticker": "AKBTY", "name": "Akbank T.A.S.", "change": "-7.94%"}, {"ticker": "GCPEF", "name": "GCL Technology Holdings Limited", "change": "-7.31%"}, {"ticker": "MRNA", "name": "Moderna, Inc.", "change": "-7.14%"}, {"ticker": "PSNY", "name": "Polestar Automotive Holding UK PLC", "change": "-6.97%"}, {"ticker": "SMCI", "name": "Super Micro Computer, Inc.", "change": "-6.95%"}, {"ticker": "TKC", "name": "Turkcell Iletisim Hizmetleri A.S.", "change": "-6.90%"}, {"ticker": "NVAX", "name": "Novavax, Inc.", "change": "-6.51%"}, {"ticker": "MGYOY", "name": "MOL Magyar Olaj- \u00e9s G\u00e1zipari Nyilv\u00e1nosan Muk\u00f6do R\u00e9szv\u00e9nyt\u00e1rsas\u00e1g", "change": "-6.40%"}, {"ticker": "RBLX", "name": "Roblox Corporation", "change": "-6.05%"}, {"ticker": "ASMVY", "name": "ASMPT Limited", "change": "-6.00%"}, {"ticker": "PEGA", "name": "Pegasystems Inc.", "change": "-6.00%"}, {"ticker": "PSNYW", "name": "Polestar Automotive Holding UK PLC", "change": "-5.92%"}, {"ticker": "COIN", "name": "Coinbase Global, Inc.", "change": "-5.50%"}, {"ticker": "OSH", "name": "Oak Street Health, Inc.", "change": "-5.45%"}, {"ticker": "MKTX", "name": "MarketAxess Holdings Inc.", "change": "-5.38%"}, {"ticker": "NVCR", "name": "NovoCure Limited", "change": "-5.35%"}, {"ticker": "PRVA", "name": "Privia Health Group, Inc.", "change": "-5.24%"}, {"ticker": "WE", "name": "WeWork Inc.", "change": "-5.23%"}, {"ticker": "JTKWY", "name": "Just Eat Takeaway.com N.V.", "change": "-5.00%"}]}