{"timestamp": "Fri Jan 13 15:22:07 2023", "loosers": [{"ticker": "PPERF", "name": "PT Bank Mandiri (Persero) Tbk", "change": "-8.52%"}, {"ticker": "LUNMF", "name": "Lundin Mining Corporation", "change": "-6.30%"}, {"ticker": "RIVN", "name": "Rivian Automotive, Inc.", "change": "-5.83%"}, {"ticker": "F", "name": "Ford Motor Company", "change": "-6.07%"}, {"ticker": "FSR", "name": "Fisker Inc.", "change": "-5.84%"}, {"ticker": "AQN", "name": "Algonquin Power & Utilities Corp.", "change": "-5.53%"}, {"ticker": "APE", "name": "AMC Entertainment Holdings, Inc.", "change": "-5.21%"}, {"ticker": "PILBF", "name": "Pilbara Minerals Limited", "change": "-5.42%"}, {"ticker": "GM", "name": "General Motors Company", "change": "-5.35%"}, {"ticker": "DAL", "name": "Delta Air Lines, Inc.", "change": "-4.47%"}, {"ticker": "LCID", "name": "Lucid Group, Inc.", "change": "-4.69%"}, {"ticker": "AN", "name": "AutoNation, Inc.", "change": "-4.49%"}, {"ticker": "SHC", "name": "Sotera Health Company", "change": "-4.49%"}, {"ticker": "WMG", "name": "Warner Music Group Corp.", "change": "-4.44%"}, {"ticker": "STLA", "name": "Stellantis N.V.", "change": "-4.18%"}, {"ticker": "NOC", "name": "Northrop Grumman Corporation", "change": "-4.10%"}, {"ticker": "VWAPY", "name": "Volkswagen AG", "change": "-3.79%"}, {"ticker": "PTEN", "name": "Patterson-UTI Energy, Inc.", "change": "-4.04%"}, {"ticker": "KEY", "name": "KeyCorp", "change": "-3.90%"}, {"ticker": "POAHY", "name": "Porsche Automobil Holding SE", "change": "-3.70%"}, {"ticker": "CWST", "name": "Casella Waste Systems, Inc.", "change": "-3.75%"}, {"ticker": "NIO", "name": "NIO Inc.", "change": "-2.90%"}, {"ticker": "SPT", "name": "Sprout Social, Inc.", "change": "-3.96%"}, {"ticker": "TSLA", "name": "Tesla, Inc.", "change": "-3.60%"}, {"ticker": "ARCC", "name": "Ares Capital Corporation", "change": "-3.53%"}]}