{"timestamp": "Fri Oct  7 18:37:35 2022", "loosers": [{"ticker": "PHJMF", "name": "PT Hanjaya Mandala Sampoerna Tbk", "change": "-15.29%"}, {"ticker": "AMD", "name": "Advanced Micro Devices, Inc.", "change": "-12.88%"}, {"ticker": "LAC", "name": "Lithium Americas Corp.", "change": "-12.32%"}, {"ticker": "RBLX", "name": "Roblox Corporation", "change": "-11.60%"}, {"ticker": "LEVI", "name": "Levi Strauss & Co.", "change": "-11.46%"}, {"ticker": "GDS", "name": "GDS Holdings Limited", "change": "-11.33%"}, {"ticker": "SPT", "name": "Sprout Social, Inc.", "change": "-11.24%"}, {"ticker": "CFLT", "name": "Confluent, Inc.", "change": "-11.12%"}, {"ticker": "MRVL", "name": "Marvell Technology, Inc.", "change": "-11.01%"}, {"ticker": "LNTH", "name": "Lantheus Holdings, Inc.", "change": "-10.92%"}, {"ticker": "COIN", "name": "Coinbase Global, Inc.", "change": "-10.91%"}, {"ticker": "ACAD", "name": "ACADIA Pharmaceuticals Inc.", "change": "-10.82%"}, {"ticker": "AFRM", "name": "Affirm Holdings, Inc.", "change": "-10.43%"}, {"ticker": "CVS", "name": "CVS Health Corporation", "change": "-10.69%"}, {"ticker": "SYNA", "name": "Synaptics Incorporated", "change": "-10.35%"}, {"ticker": "APE", "name": "AMC Entertainment Holdings, Inc.", "change": "-9.82%"}, {"ticker": "SHOP", "name": "Shopify Inc.", "change": "-10.08%"}, {"ticker": "CVNA", "name": "Carvana Co.", "change": "-9.94%"}, {"ticker": "SMG", "name": "The Scotts Miracle-Gro Company", "change": "-9.80%"}, {"ticker": "BZ", "name": "Kanzhun Limited", "change": "-9.68%"}, {"ticker": "HKD", "name": "AMTD Digital Inc.", "change": "-9.65%"}, {"ticker": "W", "name": "Wayfair Inc.", "change": "-9.57%"}, {"ticker": "NET", "name": "Cloudflare, Inc.", "change": "-9.49%"}, {"ticker": "LAZR", "name": "Luminar Technologies, Inc.", "change": "-9.31%"}, {"ticker": "AMC", "name": "AMC Entertainment Holdings, Inc.", "change": "-9.32%"}]}