{"timestamp": "Mon Aug  9 19:15:54 2021", "loosers": [{"ticker": "ELAN", "name": "Elanco Animal Health Incorporated", "change": "-16.77%"}, {"ticker": "PHJMF", "name": "PT Hanjaya Mandala Sampoerna Tbk", "change": "-3.83%"}, {"ticker": "TKGBY", "name": "Turkiye Garanti Bankasi A.S.", "change": "-6.90%"}, {"ticker": "CFEIY", "name": "China Feihe Limited", "change": "-6.71%"}, {"ticker": "MCFE", "name": "McAfee Corp.", "change": "-6.46%"}, {"ticker": "FNMAS", "name": "Federal National Mortgage Association", "change": "-5.91%"}, {"ticker": "LNNGF", "name": "Li Ning Company Limited", "change": "-5.87%"}, {"ticker": "REZI", "name": "Resideo Technologies, Inc.", "change": "-5.80%"}, {"ticker": "PRVA", "name": "Privia Health Group, Inc.", "change": "-5.76%"}, {"ticker": "VMEO", "name": "Vimeo, Inc.", "change": "-5.85%"}, {"ticker": "APD", "name": "Air Products and Chemicals, Inc.", "change": "-5.74%"}, {"ticker": "MED", "name": "Medifast, Inc.", "change": "-5.50%"}, {"ticker": "EAT", "name": "Brinker International, Inc.", "change": "-5.29%"}, {"ticker": "ONEM", "name": "1Life Healthcare, Inc.", "change": "-5.34%"}, {"ticker": "ATRC", "name": "AtriCure, Inc.", "change": "-5.33%"}, {"ticker": "BABWF", "name": "International Consolidated Airlines Group, S.A.", "change": "-5.22%"}, {"ticker": "NABL", "name": "N-able, Inc.", "change": "-4.91%"}, {"ticker": "HMY", "name": "Harmony Gold Mining Company Limited", "change": "-4.80%"}, {"ticker": "DRI", "name": "Darden Restaurants, Inc.", "change": "-4.78%"}, {"ticker": "HEI-A", "name": "HEICO Corporation", "change": "-4.66%"}, {"ticker": "LYEL", "name": "Lyell Immunopharma, Inc.", "change": "-4.83%"}, {"ticker": "AUY", "name": "Yamana Gold Inc.", "change": "-4.73%"}, {"ticker": "BHVN", "name": "Biohaven Pharmaceutical Holding Company Ltd.", "change": "-4.93%"}, {"ticker": "LSPD", "name": "Lightspeed POS Inc.", "change": "-4.82%"}, {"ticker": "CARG", "name": "CarGurus, Inc.", "change": "-4.37%"}]}