{"timestamp": "Thu Jun  9 14:20:32 2022", "loosers": [{"ticker": "PAGS", "name": "PagSeguro Digital Ltd.", "change": "-15.58%"}, {"ticker": "AUR", "name": "Aurora Innovation, Inc.", "change": "-15.98%"}, {"ticker": "ABM", "name": "ABM Industries Incorporated", "change": "-10.60%"}, {"ticker": "BPMC", "name": "Blueprint Medicines Corporation", "change": "-10.81%"}, {"ticker": "BILI", "name": "Bilibili Inc.", "change": "-9.49%"}, {"ticker": "BZ", "name": "Kanzhun Limited", "change": "-9.52%"}, {"ticker": "EDU", "name": "New Oriental Education & Technology Group Inc.", "change": "-8.63%"}, {"ticker": "TAL", "name": "TAL Education Group", "change": "-8.22%"}, {"ticker": "ZEN", "name": "Zendesk, Inc.", "change": "-8.45%"}, {"ticker": "IRTC", "name": "iRhythm Technologies, Inc.", "change": "-8.21%"}, {"ticker": "YUMC", "name": "Yum China Holdings, Inc.", "change": "-8.40%"}, {"ticker": "TRUP", "name": "Trupanion, Inc.", "change": "-7.72%"}, {"ticker": "AMBP", "name": "Ardagh Metal Packaging S.A.", "change": "-7.71%"}, {"ticker": "BEKE", "name": "KE Holdings Inc.", "change": "-6.74%"}, {"ticker": "PDD", "name": "Pinduoduo Inc.", "change": "-7.00%"}, {"ticker": "TCOM", "name": "Trip.com Group Limited", "change": "-6.98%"}, {"ticker": "STNE", "name": "StoneCo Ltd.", "change": "-6.39%"}, {"ticker": "IQ", "name": "iQIYI, Inc.", "change": "-6.29%"}, {"ticker": "ESBA", "name": "Empire State Realty OP, L.P.", "change": "0.00%"}, {"ticker": "AMR", "name": "Alpha Metallurgical Resources, Inc.", "change": "-6.34%"}, {"ticker": "UNFI", "name": "United Natural Foods, Inc.", "change": "-6.46%"}, {"ticker": "CRK", "name": "Comstock Resources, Inc.", "change": "-6.11%"}, {"ticker": "JD", "name": "JD.com, Inc.", "change": "-6.30%"}, {"ticker": "HTHT", "name": "Huazhu Group Limited", "change": "-5.95%"}, {"ticker": "NVAX", "name": "Novavax, Inc.", "change": "-5.12%"}]}