{"timestamp": "Tue Feb 21 17:18:41 2023", "loosers": [{"ticker": "ISEE", "name": "IVERIC bio, Inc.", "change": "-16.45%"}, {"ticker": "DAN", "name": "Dana Incorporated", "change": "-13.98%"}, {"ticker": "AEL", "name": "American Equity Investment Life Holding Company", "change": "-13.13%"}, {"ticker": "NDSN", "name": "Nordson Corporation", "change": "-12.45%"}, {"ticker": "ELAN", "name": "Elanco Animal Health Incorporated", "change": "-12.07%"}, {"ticker": "JD", "name": "JD.com, Inc.", "change": "-11.48%"}, {"ticker": "LAZR", "name": "Luminar Technologies, Inc.", "change": "-11.83%"}, {"ticker": "TRN", "name": "Trinity Industries, Inc.", "change": "-11.10%"}, {"ticker": "LPX", "name": "Louisiana-Pacific Corporation", "change": "-10.48%"}, {"ticker": "MANU", "name": "Manchester United plc", "change": "-10.67%"}, {"ticker": "DDS", "name": "Dillard's, Inc.", "change": "-10.34%"}, {"ticker": "LCID", "name": "Lucid Group, Inc.", "change": "-9.56%"}, {"ticker": "PDD", "name": "PDD Holdings Inc.", "change": "-9.53%"}, {"ticker": "APE", "name": "AMC Entertainment Holdings, Inc.", "change": "-9.79%"}, {"ticker": "DOCU", "name": "DocuSign, Inc.", "change": "-9.16%"}, {"ticker": "HRMY", "name": "Harmony Biosciences Holdings, Inc.", "change": "-8.85%"}, {"ticker": "PACB", "name": "Pacific Biosciences of California, Inc.", "change": "-9.47%"}, {"ticker": "SAH", "name": "Sonic Automotive, Inc.", "change": "-8.85%"}, {"ticker": "TGTX", "name": "TG Therapeutics, Inc.", "change": "-8.65%"}, {"ticker": "NPO", "name": "EnPro Industries, Inc.", "change": "-8.28%"}, {"ticker": "RARE", "name": "Ultragenyx Pharmaceutical Inc.", "change": "-8.27%"}, {"ticker": "BRPHF", "name": "Galaxy Digital Holdings Ltd.", "change": "-8.10%"}, {"ticker": "LGIH", "name": "LGI Homes, Inc.", "change": "-7.94%"}, {"ticker": "ARNC", "name": "Arconic Corporation", "change": "-7.92%"}, {"ticker": "CHWY", "name": "Chewy, Inc.", "change": "-7.87%"}]}