{"timestamp": "Wed Nov 10 19:17:24 2021", "loosers": [{"ticker": "FUBO", "name": "fuboTV Inc.", "change": null}, {"ticker": "MNDY", "name": "monday.com Ltd.", "change": null}, {"ticker": "UPST", "name": "Upstart Holdings, Inc.", "change": null}, {"ticker": "IONQ", "name": "IonQ, Inc.", "change": null}, {"ticker": "LPRO", "name": "Open Lending Corporation", "change": null}, {"ticker": "RXRX", "name": "Recursion Pharmaceuticals, Inc.", "change": null}, {"ticker": "EVGRF", "name": "China Evergrande New Energy Vehicle Group Limited", "change": null}, {"ticker": "TOST", "name": "Toast, Inc.", "change": null}, {"ticker": "AFRM", "name": "Affirm Holdings, Inc.", "change": null}, {"ticker": "SKIN", "name": "The Beauty Health Company", "change": null}, {"ticker": "OLK", "name": "Olink Holding AB (publ)", "change": null}, {"ticker": "EYE", "name": "National Vision Holdings, Inc.", "change": null}, {"ticker": "NEGG", "name": "Newegg Commerce, Inc.", "change": null}, {"ticker": "NVNXF", "name": "Novonix Limited", "change": null}, {"ticker": "SHC", "name": "Sotera Health Company", "change": null}, {"ticker": "GLBE", "name": "Global-e Online Ltd.", "change": null}, {"ticker": "MARA", "name": "Marathon Digital Holdings, Inc.", "change": null}, {"ticker": "PRGO", "name": "Perrigo Company plc", "change": null}, {"ticker": "BAK", "name": "Braskem S.A.", "change": null}, {"ticker": "EVBG", "name": "Everbridge, Inc.", "change": null}, {"ticker": "DDL", "name": "Dingdong (Cayman) Limited", "change": null}, {"ticker": "CRK", "name": "Comstock Resources, Inc.", "change": null}, {"ticker": "ROIV", "name": "Roivant Sciences Ltd.", "change": null}, {"ticker": "RBLX", "name": "Roblox Corporation", "change": null}, {"ticker": "LC", "name": "LendingClub Corporation", "change": null}]}