{"timestamp": "Thu Apr 29 19:22:37 2021", "loosers": [{"ticker": "FORM", "name": "FormFactor, Inc.", "change": "-18.16%"}, {"ticker": "CDE", "name": "Coeur Mining, Inc.", "change": "-14.36%"}, {"ticker": "AZPN", "name": "Aspen Technology, Inc.", "change": "-12.71%"}, {"ticker": "MVIS", "name": "MicroVision, Inc.", "change": "-12.46%"}, {"ticker": "CREE", "name": "Cree, Inc.", "change": "-11.77%"}, {"ticker": "LYFT", "name": "Lyft, Inc.", "change": "-11.48%"}, {"ticker": "EM", "name": "Smart Share Global Limited", "change": "-10.75%"}, {"ticker": "TREE", "name": "LendingTree, Inc.", "change": "-10.92%"}, {"ticker": "CAN", "name": "Canaan Inc.", "change": "-10.87%"}, {"ticker": "EBAY", "name": "eBay Inc.", "change": "-10.00%"}, {"ticker": "PTC", "name": "PTC Inc.", "change": "-9.79%"}, {"ticker": "TDOC", "name": "Teladoc Health, Inc.", "change": "-9.14%"}, {"ticker": "RLX", "name": "RLX Technology Inc.", "change": "-8.41%"}, {"ticker": "MEOH", "name": "Methanex Corporation", "change": "-8.99%"}, {"ticker": "MARA", "name": "Marathon Digital Holdings, Inc.", "change": "-8.97%"}, {"ticker": "AR", "name": "Antero Resources Corporation", "change": "-8.85%"}, {"ticker": "KC", "name": "Kingsoft Cloud Holdings Limited", "change": "-8.49%"}, {"ticker": "DOYU", "name": "DouYu International Holdings Limited", "change": "-8.48%"}, {"ticker": "RIOT", "name": "Riot Blockchain, Inc.", "change": "-8.72%"}, {"ticker": "VNET", "name": "21Vianet Group, Inc.", "change": "-8.32%"}, {"ticker": "NOW", "name": "ServiceNow, Inc.", "change": "-8.41%"}, {"ticker": "XM", "name": "Qualtrics International Inc.", "change": "-8.23%"}, {"ticker": "ALLO", "name": "Allogene Therapeutics, Inc.", "change": "-8.35%"}, {"ticker": "ASH", "name": "Ashland Global Holdings Inc.", "change": "-8.09%"}, {"ticker": "DASH", "name": "DoorDash, Inc.", "change": "-8.28%"}]}