{"timestamp": "Tue Aug 31 16:32:56 2021", "loosers": [{"ticker": "BPIRY", "name": "Piraeus Financial Holdings S.A.", "change": "-21.88%"}, {"ticker": "GSAT", "name": "Globalstar, Inc.", "change": "-17.46%"}, {"ticker": "ZM", "name": "Zoom Video Communications, Inc.", "change": "-16.34%"}, {"ticker": "FIVN", "name": "Five9, Inc.", "change": "-14.78%"}, {"ticker": "HEPS", "name": "D-MARKET Elektronik Hizmetler ve Ticaret Anonim Sirketi", "change": "-10.14%"}, {"ticker": "MD", "name": "MEDNAX, Inc.", "change": "-7.62%"}, {"ticker": "IRDM", "name": "Iridium Communications Inc.", "change": "-7.38%"}, {"ticker": "AGL", "name": "agilon health, inc.", "change": "-7.44%"}, {"ticker": "CRTX", "name": "Cortexyme, Inc.", "change": "-6.85%"}, {"ticker": "AFRM", "name": "Affirm Holdings, Inc.", "change": "-6.47%"}, {"ticker": "CVAC", "name": "CureVac N.V.", "change": "-6.61%"}, {"ticker": "NXPI", "name": "NXP Semiconductors N.V.", "change": "-5.92%"}, {"ticker": "TMVWY", "name": "TeamViewer AG", "change": "-5.64%"}, {"ticker": "CDNA", "name": "CareDx, Inc", "change": "-5.49%"}, {"ticker": "SEMR", "name": "SEMrush Holdings, Inc.", "change": "-5.44%"}, {"ticker": "YOU", "name": "Clear Secure, Inc.", "change": "-5.52%"}, {"ticker": "TSP", "name": "TuSimple Holdings Inc.", "change": "-5.14%"}, {"ticker": "COMP", "name": "Compass, Inc.", "change": "-5.27%"}, {"ticker": "BLI", "name": "Berkeley Lights, Inc.", "change": "-5.25%"}, {"ticker": "STNE", "name": "StoneCo Ltd.", "change": "-4.99%"}, {"ticker": "BHG", "name": "Bright Health Group, Inc.", "change": "-5.17%"}, {"ticker": "BABWF", "name": "International Consolidated Airlines Group, S.A.", "change": "-4.93%"}, {"ticker": "CTOS", "name": "Custom Truck One Source, Inc.", "change": "-5.26%"}, {"ticker": "DDL", "name": "Dingdong (Cayman) Limited", "change": "-5.58%"}, {"ticker": "DQ", "name": "Daqo New Energy Corp.", "change": "-4.77%"}]}