{"timestamp": "Wed Jan  5 14:17:17 2022", "loosers": [{"ticker": "VALN", "name": "Valneva SE", "change": null}, {"ticker": "ITCI", "name": "Intra-Cellular Therapies, Inc.", "change": null}, {"ticker": "LU", "name": "Lufax Holding Ltd", "change": null}, {"ticker": "GLBE", "name": "Global-e Online Ltd.", "change": null}, {"ticker": "DADA", "name": "Dada Nexus Limited", "change": null}, {"ticker": "STNE", "name": "StoneCo Ltd.", "change": null}, {"ticker": "SE", "name": "Sea Limited", "change": null}, {"ticker": "VCYT", "name": "Veracyte, Inc.", "change": null}, {"ticker": "CNM", "name": "Core & Main, Inc.", "change": null}, {"ticker": "PDD", "name": "Pinduoduo Inc.", "change": null}, {"ticker": "RGEN", "name": "Repligen Corporation", "change": null}, {"ticker": "FUTU", "name": "Futu Holdings Limited", "change": null}, {"ticker": "OLK", "name": "Olink Holding AB (publ)", "change": null}, {"ticker": "BRZE", "name": "Braze, Inc.", "change": null}, {"ticker": "MRVI", "name": "Maravai LifeSciences Holdings, Inc.", "change": null}, {"ticker": "BEKE", "name": "KE Holdings Inc.", "change": null}, {"ticker": "IAS", "name": "Integral Ad Science Holding Corp.", "change": null}, {"ticker": "ENVX", "name": "Enovix Corporation", "change": null}, {"ticker": "DAVA", "name": "Endava plc", "change": null}, {"ticker": "SHOP", "name": "Shopify Inc.", "change": null}, {"ticker": "AFRM", "name": "Affirm Holdings, Inc.", "change": null}, {"ticker": "PAGS", "name": "PagSeguro Digital Ltd.", "change": null}, {"ticker": "FLGT", "name": "Fulgent Genetics, Inc.", "change": null}, {"ticker": "PAY", "name": "Paymentus Holdings, Inc.", "change": null}, {"ticker": "GDS", "name": "GDS Holdings Limited", "change": null}]}