{"timestamp": "Mon Mar 20 17:18:25 2023", "loosers": [{"ticker": "CS", "name": "Credit Suisse Group AG", "change": "-51.84%"}, {"ticker": "CSGKF", "name": "Credit Suisse Group AG", "change": "-51.34%"}, {"ticker": "FRC", "name": "First Republic Bank", "change": "-26.79%"}, {"ticker": "MNGPF", "name": "Man Group Limited", "change": "-21.35%"}, {"ticker": "FRC-PI", "name": "First Republic Bank", "change": "-15.17%"}, {"ticker": "PDD", "name": "PDD Holdings Inc.", "change": "-12.94%"}, {"ticker": "FRC-PH", "name": "First Republic Bank", "change": "-10.79%"}, {"ticker": "ZLAB", "name": "Zai Lab Limited", "change": "-9.82%"}, {"ticker": "JAMF", "name": "Jamf Holding Corp.", "change": "-7.43%"}, {"ticker": "PTON", "name": "Peloton Interactive, Inc.", "change": "-6.55%"}, {"ticker": "VERX", "name": "Vertex, Inc.", "change": "-6.33%"}, {"ticker": "NTCO", "name": "Natura &Co Holding S.A.", "change": "-6.27%"}, {"ticker": "LAZR", "name": "Luminar Technologies, Inc.", "change": "-6.19%"}, {"ticker": "KRTX", "name": "Karuna Therapeutics, Inc.", "change": "-5.94%"}, {"ticker": "PBI-PB", "name": "Pitney Bowes Inc. NT 43", "change": "-5.90%"}, {"ticker": "TBVPF", "name": "Thai Beverage Public Company Limited", "change": "-5.62%"}, {"ticker": "LIFW", "name": "MSP Recovery, Inc.", "change": "-5.32%"}, {"ticker": "RNG", "name": "RingCentral, Inc.", "change": "-5.22%"}, {"ticker": "DOCU", "name": "DocuSign, Inc.", "change": "-5.22%"}, {"ticker": "FL", "name": "Foot Locker, Inc.", "change": "-4.78%"}, {"ticker": "GH", "name": "Guardant Health, Inc.", "change": "-5.05%"}, {"ticker": "TEAM", "name": "Atlassian Corporation", "change": "-4.63%"}, {"ticker": "HCM", "name": "HUTCHMED (China) Limited", "change": "-4.77%"}, {"ticker": "AL-PA", "name": "Air Lease Corporation", "change": "-4.67%"}, {"ticker": "LSRCY", "name": "Lasertec Corporation", "change": "-4.62%"}]}