{"timestamp": "Mon Nov 28 16:25:38 2022", "loosers": [{"ticker": "SAPMD", "name": "Saipem SpA", "change": "-28.99%"}, {"ticker": "CSGKF", "name": "Credit Suisse Group AG", "change": "-10.42%"}, {"ticker": "LINRF", "name": "Liontown Resources Limited", "change": "-10.34%"}, {"ticker": "PSNY", "name": "Polestar Automotive Holding UK PLC", "change": "-9.74%"}, {"ticker": "PHJMF", "name": "PT Hanjaya Mandala Sampoerna Tbk", "change": "-7.42%"}, {"ticker": "PROK", "name": "ProKidney Corp.", "change": "-7.11%"}, {"ticker": "APE", "name": "AMC Entertainment Holdings, Inc.", "change": "-6.56%"}, {"ticker": "SBLK", "name": "Star Bulk Carriers Corp.", "change": "-6.42%"}, {"ticker": "TPRKY", "name": "Travis Perkins plc", "change": "-6.16%"}, {"ticker": "ARRY", "name": "Array Technologies, Inc.", "change": "-6.19%"}, {"ticker": "TRUP", "name": "Trupanion, Inc.", "change": "-5.48%"}, {"ticker": "EURN", "name": "Euronav NV", "change": "-5.63%"}, {"ticker": "PR", "name": "Permian Resources Corporation", "change": "-5.23%"}, {"ticker": "DNA", "name": "Ginkgo Bioworks Holdings, Inc.", "change": "-5.25%"}, {"ticker": "DLO", "name": "DLocal Limited", "change": "-5.31%"}, {"ticker": "SGRY", "name": "Surgery Partners, Inc.", "change": "-5.60%"}, {"ticker": "EVA", "name": "Enviva Inc.", "change": "-5.25%"}, {"ticker": "CSIQ", "name": "Canadian Solar Inc.", "change": "-5.30%"}, {"ticker": "AG", "name": "First Majestic Silver Corp.", "change": "-4.96%"}, {"ticker": "HL", "name": "Hecla Mining Company", "change": "-5.20%"}, {"ticker": "FRO", "name": "Frontline Ltd.", "change": "-5.16%"}, {"ticker": "QS", "name": "QuantumScape Corporation", "change": "-5.05%"}, {"ticker": "CHPT", "name": "ChargePoint Holdings, Inc.", "change": "-4.96%"}, {"ticker": "INSW", "name": "International Seaways, Inc.", "change": "-4.87%"}, {"ticker": "EADSY", "name": "Airbus SE", "change": "-4.87%"}]}